NiukeShujuFenxishiQiuzhiJingyanFenxiang20212022Fix1/README.md
NiukeShujuFenxishiQiuzhiJingyanFenxiang20212022Fix1/__init__.py
NiukeShujuFenxishiQiuzhiJingyanFenxiang20212022Fix1/__main__.py
NiukeShujuFenxishiQiuzhiJingyanFenxiang20212022Fix1/file.epub
NiukeShujuFenxishiQiuzhiJingyanFenxiang20212022Fix1/index.html
NiukeShujuFenxishiQiuzhiJingyanFenxiang20212022Fix1/css/__init__.py
NiukeShujuFenxishiQiuzhiJingyanFenxiang20212022Fix1/css/annotations.css
NiukeShujuFenxishiQiuzhiJingyanFenxiang20212022Fix1/css/main.css
NiukeShujuFenxishiQiuzhiJingyanFenxiang20212022Fix1/css/normalize.css
NiukeShujuFenxishiQiuzhiJingyanFenxiang20212022Fix1/css/popup.css
NiukeShujuFenxishiQiuzhiJingyanFenxiang20212022Fix1/font/__init__.py
NiukeShujuFenxishiQiuzhiJingyanFenxiang20212022Fix1/font/fontello.eot
NiukeShujuFenxishiQiuzhiJingyanFenxiang20212022Fix1/font/fontello.svg
NiukeShujuFenxishiQiuzhiJingyanFenxiang20212022Fix1/font/fontello.ttf
NiukeShujuFenxishiQiuzhiJingyanFenxiang20212022Fix1/font/fontello.woff
NiukeShujuFenxishiQiuzhiJingyanFenxiang20212022Fix1/img/__init__.py
NiukeShujuFenxishiQiuzhiJingyanFenxiang20212022Fix1/img/annotator-glyph-sprite.png
NiukeShujuFenxishiQiuzhiJingyanFenxiang20212022Fix1/img/annotator-icon-sprite.png
NiukeShujuFenxishiQiuzhiJingyanFenxiang20212022Fix1/img/apple-touch-icon.png
NiukeShujuFenxishiQiuzhiJingyanFenxiang20212022Fix1/img/cancelfullscreen.png
NiukeShujuFenxishiQiuzhiJingyanFenxiang20212022Fix1/img/close.png
NiukeShujuFenxishiQiuzhiJingyanFenxiang20212022Fix1/img/fullscreen.png
NiukeShujuFenxishiQiuzhiJingyanFenxiang20212022Fix1/img/loader.gif
NiukeShujuFenxishiQiuzhiJingyanFenxiang20212022Fix1/img/menu-icon.png
NiukeShujuFenxishiQiuzhiJingyanFenxiang20212022Fix1/img/save.png
NiukeShujuFenxishiQiuzhiJingyanFenxiang20212022Fix1/img/saved.png
NiukeShujuFenxishiQiuzhiJingyanFenxiang20212022Fix1/img/settings-s.png
NiukeShujuFenxishiQiuzhiJingyanFenxiang20212022Fix1/img/settings.png
niuke_shuju_fenxishi_qiuzhi_jingyan_fenxiang_2021_2022_fix1-2025.3.25.1.dist-info/METADATA
niuke_shuju_fenxishi_qiuzhi_jingyan_fenxiang_2021_2022_fix1-2025.3.25.1.dist-info/WHEEL
niuke_shuju_fenxishi_qiuzhi_jingyan_fenxiang_2021_2022_fix1-2025.3.25.1.dist-info/entry_points.txt
niuke_shuju_fenxishi_qiuzhi_jingyan_fenxiang_2021_2022_fix1-2025.3.25.1.dist-info/top_level.txt
niuke_shuju_fenxishi_qiuzhi_jingyan_fenxiang_2021_2022_fix1-2025.3.25.1.dist-info/RECORD
